django_autocode_tools/__init__.py
django_autocode_tools/app_settings.py
django_autocode_tools/auto_code.py
django_autocode_tools/management/__init__.py
django_autocode_tools/management/commands/__init__.py
django_autocode_tools/management/commands/auto_code.py
django_autocode_tools/templates/__init__.py
django_autocode_tools/templates/orm
django_autocode_tools/templates/ser
django_autocode_tools/templates/view
django_autocode_tools/wrapper/__init__.py
django_autocode_tools/wrapper/http_wrapper.py
management/__init__.py
management/commands/__init__.py
management/commands/auto_code.py
wrapper/__init__.py
wrapper/http_wrapper.py
django_autocode_tools-0.0.4.dist-info/METADATA
django_autocode_tools-0.0.4.dist-info/WHEEL
django_autocode_tools-0.0.4.dist-info/top_level.txt
django_autocode_tools-0.0.4.dist-info/RECORD
